openarchx/__init__.py
openarchx/algorithms/linear_attention.py
openarchx/algorithms/sparse_gradients.py
openarchx/bayesian/variational_inference.py
openarchx/core/memory_optimized_tensor.py
openarchx/core/quantum_sparse_engine.py
openarchx/core/tensor.py
openarchx/cuda/__init__.py
openarchx/cuda/bindings.cpp
openarchx/cuda/cuda_ops.py
openarchx/cuda/kernels.cu
openarchx/cuda/test_cuda.py
openarchx/data/adaptive_compression.py
openarchx/layers/activations.py
openarchx/layers/base.py
openarchx/layers/cnn.py
openarchx/layers/transformer.py
openarchx/nn/__init__.py
openarchx/nn/activations.py
openarchx/nn/containers.py
openarchx/nn/dropout.py
openarchx/nn/layers.py
openarchx/nn/losses.py
openarchx/nn/module.py
openarchx/nn/padding.py
openarchx/nn/pooling.py
openarchx/nn/rnn.py
openarchx/nn/transformers.py
openarchx/optimizers/__init__.py
openarchx/optimizers/adam.py
openarchx/optimizers/adaptive.py
openarchx/optimizers/base.py
openarchx/optimizers/modern.py
openarchx/optimizers/optx.py
openarchx/optimizers/probabilistic.py
openarchx/optimizers/sgd.py
openarchx/quantum/circuit.py
openarchx/quantum/gates.py
openarchx/training/cpu_accelerator.py
openarchx/utils/__init__.py
openarchx/utils/data.py
openarchx/utils/error_handler.py
openarchx/utils/huggingface.py
openarchx/utils/losses.py
openarchx/utils/model_io.py
openarchx/utils/pytorch.py
openarchx/utils/tensorflow.py
openarchx/utils/transforms.py
openarchx_revolutionary-0.1.3.dist-info/licenses/LICENSE.md
tests/__init__.py
tests/test_cuda_ops.py
tests/test_integrations.py
tests/test_probabilistic_integration.py
tests/test_probabilistic_optimization.py
openarchx_revolutionary-0.1.3.dist-info/METADATA
openarchx_revolutionary-0.1.3.dist-info/WHEEL
openarchx_revolutionary-0.1.3.dist-info/top_level.txt
openarchx_revolutionary-0.1.3.dist-info/RECORD
