Metadata-Version: 2.4
Name: openarchx-revolutionary
Version: 0.1.3
Summary: Revolutionary deep learning framework with quantum-inspired computing, O(n) attention, 90% data compression, and 70% gradient reduction
Home-page: https://github.com/openarchx/openarchx
Author: OpenArchX Team
Author-email: OpenArchX Team <info@openarchx.org>
License: MIT
Project-URL: Homepage, https://github.com/openarchx/openarchx
Project-URL: Bug Tracker, https://github.com/openarchx/openarchx/issues
Keywords: deep learning,machine learning,neural networks,quantum computing,attention,compression,sparse gradients,AI,pytorch alternative
Classifier: Development Status :: 4 - Beta
Classifier: Intended Audience :: Developers
Classifier: Intended Audience :: Science/Research
Classifier: License :: OSI Approved :: MIT License
Classifier: Programming Language :: Python :: 3
Classifier: Programming Language :: Python :: 3.7
Classifier: Programming Language :: Python :: 3.8
Classifier: Programming Language :: Python :: 3.9
Classifier: Programming Language :: Python :: 3.10
Classifier: Programming Language :: Python :: 3.11
Classifier: Topic :: Scientific/Engineering :: Artificial Intelligence
Classifier: Topic :: Software Development :: Libraries :: Python Modules
Classifier: Operating System :: OS Independent
Requires-Python: >=3.7
License-File: LICENSE.md
Requires-Dist: numpy>=1.19.0
Requires-Dist: scipy>=1.7.0
Requires-Dist: psutil>=5.8.0
Provides-Extra: pytorch
Requires-Dist: torch>=1.7.0; extra == "pytorch"
Provides-Extra: tensorflow
Requires-Dist: tensorflow>=2.4.0; extra == "tensorflow"
Provides-Extra: huggingface
Requires-Dist: transformers>=4.0.0; extra == "huggingface"
Requires-Dist: datasets>=1.0.0; extra == "huggingface"
Provides-Extra: all
Requires-Dist: torch>=1.7.0; extra == "all"
Requires-Dist: tensorflow>=2.4.0; extra == "all"
Requires-Dist: transformers>=4.0.0; extra == "all"
Requires-Dist: datasets>=1.0.0; extra == "all"
Dynamic: author
Dynamic: home-page
Dynamic: license-file
Dynamic: requires-python
